{
  "labels": [
    "Non-Drone",
    "DJI Mavic 3",
    "DJI Air 3",
    "DJI Mini 4 Pro",
    "DJI Phantom 4 Pro",
    "Autel EVO II Pro",
    "Skydio 2+",
    "DJI Air 2S",
    "DJI Mini 3 Pro",
    "Parrot Anafi",
    "DJI Inspire 2"
  ],
  "label_to_idx": {
    "Non-Drone": 0,
    "DJI Mavic 3": 1,
    "DJI Air 3": 2,
    "DJI Mini 4 Pro": 3,
    "DJI Phantom 4 Pro": 4,
    "Autel EVO II Pro": 5,
    "Skydio 2+": 6,
    "DJI Air 2S": 7,
    "DJI Mini 3 Pro": 8,
    "Parrot Anafi": 9,
    "DJI Inspire 2": 10
  },
  "num_classes": 11
}